jupyterlab_v4_codio_ext/__init__.py
jupyterlab_v4_codio_ext/_version.py
jupyterlab_v4_codio_ext-0.1.17.data/data/share/jupyter/labextensions/jupyterlab-v4-codio-ext/package.json
jupyterlab_v4_codio_ext-0.1.17.data/data/share/jupyter/labextensions/jupyterlab-v4-codio-ext/schemas/jupyterlab-v4-codio-ext/package.json.orig
jupyterlab_v4_codio_ext-0.1.17.data/data/share/jupyter/labextensions/jupyterlab-v4-codio-ext/schemas/jupyterlab-v4-codio-ext/plugin.json
jupyterlab_v4_codio_ext-0.1.17.data/data/share/jupyter/labextensions/jupyterlab-v4-codio-ext/static/728.2af6074e29d3bbe2a479.js
jupyterlab_v4_codio_ext-0.1.17.data/data/share/jupyter/labextensions/jupyterlab-v4-codio-ext/static/776.d5ec6b4804937a766fac.js
jupyterlab_v4_codio_ext-0.1.17.data/data/share/jupyter/labextensions/jupyterlab-v4-codio-ext/static/remoteEntry.53c5d9e7cf77851aeeb5.js
jupyterlab_v4_codio_ext-0.1.17.data/data/share/jupyter/labextensions/jupyterlab-v4-codio-ext/static/style.js
jupyterlab_v4_codio_ext-0.1.17.data/data/share/jupyter/labextensions/jupyterlab-v4-codio-ext/static/third-party-licenses.json
jupyterlab_v4_codio_ext-0.1.17.data/data/share/jupyter/labextensions/jupyterlab-v4-codio-ext/install.json
jupyterlab_v4_codio_ext-0.1.17.dist-info/METADATA
jupyterlab_v4_codio_ext-0.1.17.dist-info/WHEEL
jupyterlab_v4_codio_ext-0.1.17.dist-info/licenses/LICENSE
jupyterlab_v4_codio_ext-0.1.17.dist-info/RECORD
