Metadata-Version: 2.4
Name: jupyterlab_v4_codio_ext
Version: 0.1.17
Dynamic: Keywords
Summary: A JupyterLab v4 extension to interact with codio.
Project-URL: Homepage, https://github.com/codio/jupyterlab4-codio-ext
Project-URL: Bug Tracker, https://github.com/codio/jupyterlab4-codio-ext/issues
Project-URL: Repository, https://github.com/codio/jupyterlab4-codio-ext.git
Author-email: codio <support@codio.com>
License: BSD 3-Clause License
License-File: LICENSE
Classifier: Framework :: Jupyter
Classifier: Framework :: Jupyter :: JupyterLab
Classifier: Framework :: Jupyter :: JupyterLab :: 4
Classifier: Framework :: Jupyter :: JupyterLab :: Extensions
Classifier: Framework :: Jupyter :: JupyterLab :: Extensions :: Prebuilt
Classifier: License :: OSI Approved :: BSD License
Classifier: Programming Language :: Python
Classifier: Programming Language :: Python :: 3
Classifier: Programming Language :: Python :: 3.8
Classifier: Programming Language :: Python :: 3.9
Classifier: Programming Language :: Python :: 3.10
Classifier: Programming Language :: Python :: 3.11
Classifier: Programming Language :: Python :: 3.12
Requires-Python: >=3.8
